README.md
setup.cfg
setup.py
django_server_conn_pool/__init__.py
django_server_conn_pool.egg-info/PKG-INFO
django_server_conn_pool.egg-info/SOURCES.txt
django_server_conn_pool.egg-info/dependency_links.txt
django_server_conn_pool.egg-info/requires.txt
django_server_conn_pool.egg-info/top_level.txt
django_server_conn_pool/mysql/__init__.py
django_server_conn_pool/mysql/base.py