Metadata-Version: 1.1
Name: django-server-conn-pool
Version: 2.0
Summary: DB Server Connection Pooling with Django and SQL Alchemy
Home-page: https://github.com/prudhviraju-011/django-server-conn-pool
Author: raju
Author-email: ramisetty.prudhviraju@gmail.com
License: MIT
Download-URL: https://github.com/prudhviraju-011/django-server-conn-pool/archive/v2.0.tar.gz
Keywords: conn-pool
Platform: UNKNOWN
Classifier: Programming Language :: Python :: 3
Classifier: License :: OSI Approved :: MIT License
Classifier: Operating System :: OS Independent
